{"name": "burrito,_fagioli_e_formaggio,_surgelato", "Principali": {"Calorie": {"unit": "kj", "amount": "882"}, "Grassi": {"unit": "g", "amount": "5.94"}, "Carboidrati": {"unit": "g", "amount": "32.4"}, "Proteine": {"unit": "g", "amount": "6.92"}, "Fibre": {"unit": "g", "amount": "10.2"}, "Zuccheri": {"unit": "g", "amount": "1.41"}, "Acqua": {"unit": "g", "amount": "53.05"}, "Amido": {"unit": "g", "amount": "5.48"}, "Ceneri": {"unit": "g", "amount": "1.69"}}, "Minerali": {"Calcio": {"unit": "mg", "amount": "42"}, "Sodio": {"unit": "mg", "amount": "412"}, "Fosforo": {"unit": "mg", "amount": "66"}, "Potassio": {"unit": "mg", "amount": "217"}, "Ferro": {"unit": "mg", "amount": "2.78"}, "Magnesio": {"unit": "mg", "amount": "26"}, "Zinco": {"unit": "mg", "amount": "0.68"}, "Rame": {"unit": "mg", "amount": "0.146"}, "Manganese": {"unit": "mg", "amount": "0.363"}, "Selenio": {"unit": "mcg", "amount": "11.3"}}, "Vitamine": {"Retinolo (Vit. A)": {"unit": "mcg", "amount": "47"}, "Vitamina A, IU": {"unit": "IU", "amount": "189"}, "Vitamina A, RAE": {"unit": "mcg_RAE", "amount": "49"}, "Tiamina (Vit. B1)": {"unit": "mg", "amount": "0.333"}, "Riboflavina (Vit. B2)": {"unit": "mg", "amount": "0.142"}, "Niacina (Vit. B3)": {"unit": "mg", "amount": "2.167"}, "Piridossina (Vit. B6)": {"unit": "mg", "amount": "0.084"}, "Acido folico (Vit. B9 o M o Folacina)": {"unit": "mcg", "amount": "55"}, "Folato alimentare": {"unit": "mcg", "amount": "8"}, "Folato, DFE": {"unit": "mcg_DFE", "amount": "102"}, "Folati, totali": {"unit": "mcg", "amount": "63"}, "Acido ascorbico (Vit. C)": {"unit": "mg", "amount": "0"}, "Fillochinone (Vit. K)": {"unit": "mcg", "amount": "6.2"}, "Colina totale (Vit. J)": {"unit": "mg", "amount": "22.3"}, "Carotene, beta": {"unit": "mcg", "amount": "18"}, "Carotene, alfa": {"unit": "mcg", "amount": "0"}, "Criptoxantina, beta": {"unit": "mcg", "amount": "0"}, "Licopene": {"unit": "mcg", "amount": "0"}, "Luteina + zeaxantina": {"unit": "mcg", "amount": "12"}}, "Zuccheri": {"Destrosio": {"unit": "g", "amount": "0"}, "Fruttosio": {"unit": "g", "amount": "0"}, "Galattosio": {"unit": "g", "amount": "0"}, "Lattosio": {"unit": "g", "amount": "0"}, "Maltosio": {"unit": "g", "amount": "1.06"}, "Saccarosio": {"unit": "g", "amount": "0.35"}}, "Lipidi": {"Acidi grassi, monoinsaturi": {"unit": "g", "amount": "2.262"}, "Acidi grassi, polinsaturi": {"unit": "g", "amount": "1.443"}, "Acidi grassi, saturi": {"unit": "g", "amount": "1.573"}}, "Grassi saturi": {"4:0": {"unit": "g", "amount": "0"}, "6:0": {"unit": "g", "amount": "0"}, "8:0": {"unit": "g", "amount": "0"}, "Grassi Saturi 10:0": {"unit": "g", "amount": "0"}, "Grassi Saturi 12:0": {"unit": "g", "amount": "0"}, "Grassi Saturi 14:0": {"unit": "g", "amount": "0.104"}, "Grassi Saturi 15:0": {"unit": "g", "amount": "0"}, "Grassi Saturi 16:0": {"unit": "g", "amount": "0.93"}, "Grassi Saturi 17:0": {"unit": "g", "amount": "0"}, "Grassi Saturi 18:0": {"unit": "g", "amount": "0.539"}, "Grassi Saturi 20:0": {"unit": "g", "amount": "0"}, "Grassi Saturi 22:0": {"unit": "g", "amount": "0"}, "Grassi Saturi 24:0": {"unit": "g", "amount": "0"}}, "Grassi monoinsaturi": {"Grassi Monoinsaturi 14:1": {"unit": "g", "amount": "0"}, "Grassi Monoinsaturi 16:1 indifferenziato": {"unit": "g", "amount": "0"}, "Grassi Monoinsaturi 18:1 indifferenziato": {"unit": "g", "amount": "2.262"}, "Grassi Monoinsaturi 20:1": {"unit": "g", "amount": "0"}, "Grassi Monoinsaturi 22:1 indifferenziato": {"unit": "g", "amount": "0"}}, "Grassi polinsaturi": {"Grassi Polinsaturi 18:2 indifferenziato": {"unit": "g", "amount": "1.285"}, "Grassi Polinsaturi 18:3 indifferenziato": {"unit": "g", "amount": "0.158"}, "Grassi Polinsaturi 18:4": {"unit": "g", "amount": "0"}, "Grassi Polinsaturi 20:4 indifferenziato": {"unit": "g", "amount": "0"}, "20:5 n-3": {"unit": "g", "amount": "0"}, "22:5 n-3": {"unit": "g", "amount": "0"}, "22:6 n-3": {"unit": "g", "amount": "0"}}, "Aminoacidi": {"Acido aspartico": {"unit": "g", "amount": "0.334"}, "Acido glutammico": {"unit": "g", "amount": "1.998"}, "Alanina": {"unit": "g", "amount": "0.216"}, "Arginina": {"unit": "g", "amount": "0.268"}, "Cistina": {"unit": "g", "amount": "0.117"}, "Fenilalanina": {"unit": "g", "amount": "0.331"}, "Glicina": {"unit": "g", "amount": "0.22"}, "Isoleucina": {"unit": "g", "amount": "0.258"}, "Istidina": {"unit": "g", "amount": "0.159"}, "Leucina": {"unit": "g", "amount": "0.479"}, "Lisina": {"unit": "g", "amount": "0.229"}, "Metionina": {"unit": "g", "amount": "0.122"}, "Prolina": {"unit": "g", "amount": "0.714"}, "Serina": {"unit": "g", "amount": "0.336"}, "Tirosina": {"unit": "g", "amount": "0.213"}, "Treonina": {"unit": "g", "amount": "0.193"}, "Triptofano": {"unit": "g", "amount": "0.08"}, "Valina": {"unit": "g", "amount": "0.296"}}, "meta-data": ["pasti completi", "antipasti e contorni"]}