{"name": "cappuccino_istantaneo_in_polvere,_zuccherato", "Principali": {"Calorie": {"unit": "kj", "amount": "1699"}, "Grassi": {"unit": "g", "amount": "5.56"}, "Carboidrati": {"unit": "g", "amount": "85.94"}, "Proteine": {"unit": "g", "amount": "3.1"}, "Fibre": {"unit": "g", "amount": "1.2"}, "Zuccheri": {"unit": "g", "amount": "69.16"}, "Acqua": {"unit": "g", "amount": "1.3"}, "Ceneri": {"unit": "g", "amount": "4.1"}}, "Minerali": {"Calcio": {"unit": "mg", "amount": "133"}, "Sodio": {"unit": "mg", "amount": "180"}, "Fosforo": {"unit": "mg", "amount": "183"}, "Potassio": {"unit": "mg", "amount": "831"}, "Ferro": {"unit": "mg", "amount": "0.48"}, "Magnesio": {"unit": "mg", "amount": "43"}, "Zinco": {"unit": "mg", "amount": "0.25"}, "Rame": {"unit": "mg", "amount": "0.11"}, "Manganese": {"unit": "mg", "amount": "0.2"}, "Selenio": {"unit": "mcg", "amount": "4.2"}}, "Vitamine": {"Retinolo (Vit. A)": {"unit": "mcg", "amount": "0"}, "Vitamina A, IU": {"unit": "IU", "amount": "1"}, "Vitamina A, RAE": {"unit": "mcg_RAE", "amount": "0"}, "Tiamina (Vit. B1)": {"unit": "mg", "amount": "0.111"}, "Riboflavina (Vit. B2)": {"unit": "mg", "amount": "0.037"}, "Niacina (Vit. B3)": {"unit": "mg", "amount": "2.262"}, "Acido Pantotenico (Vit. B5)": {"unit": "mg", "amount": "0.073"}, "Piridossina (Vit. B6)": {"unit": "mg", "amount": "0.036"}, "Acido folico (Vit. B9 o M o Folacina)": {"unit": "mcg", "amount": "0"}, "Folato alimentare": {"unit": "mcg", "amount": "5"}, "Folato, DFE": {"unit": "mcg_DFE", "amount": "5"}, "Folati, totali": {"unit": "mcg", "amount": "5"}, "Cobalamina (Vit. B12)": {"unit": "mcg", "amount": "0.38"}, "Vitamina B-12, aggiunta": {"unit": "mcg", "amount": "0"}, "Acido ascorbico (Vit. C)": {"unit": "mg", "amount": "0.5"}, "Vitamina D (D2+D3)": {"unit": "mcg", "amount": "0"}, "Colecalcifenolo (Vit. D)": {"unit": "IU", "amount": "0"}, "Alpha-tocoferolo (Vit. E)": {"unit": "mg", "amount": "0.36"}, "Vitamina E, aggiunta": {"unit": "mg", "amount": "0"}, "Fillochinone (Vit. K)": {"unit": "mcg", "amount": "1.3"}, "Colina totale (Vit. J)": {"unit": "mg", "amount": "68"}, "Carotene, beta": {"unit": "mcg", "amount": "0"}, "Carotene, alfa": {"unit": "mcg", "amount": "0"}, "Criptoxantina, beta": {"unit": "mcg", "amount": "0"}, "Licopene": {"unit": "mcg", "amount": "0"}, "Luteina + zeaxantina": {"unit": "mcg", "amount": "0"}}, "Lipidi": {"Acidi grassi, monoinsaturi": {"unit": "g", "amount": "1.604"}, "Acidi grassi, polinsaturi": {"unit": "g", "amount": "0.241"}, "Acidi grassi, saturi": {"unit": "g", "amount": "3.422"}, "Colesterolo": {"unit": "mg", "amount": "2"}}, "Grassi saturi": {"4:0": {"unit": "g", "amount": "0.006"}, "6:0": {"unit": "g", "amount": "0.011"}, "8:0": {"unit": "g", "amount": "0.125"}, "Grassi Saturi 10:0": {"unit": "g", "amount": "0.093"}, "Grassi Saturi 12:0": {"unit": "g", "amount": "0.722"}, "Grassi Saturi 13:0": {"unit": "g", "amount": "0"}, "Grassi Saturi 14:0": {"unit": "g", "amount": "0.289"}, "Grassi Saturi 15:0": {"unit": "g", "amount": "0.003"}, "Grassi Saturi 16:0": {"unit": "g", "amount": "1.008"}, "Grassi Saturi 17:0": {"unit": "g", "amount": "0.009"}, "Grassi Saturi 18:0": {"unit": "g", "amount": "1.097"}, "Grassi Saturi 20:0": {"unit": "g", "amount": "0.028"}, "Grassi Saturi 22:0": {"unit": "g", "amount": "0.026"}, "Grassi Saturi 24:0": {"unit": "g", "amount": "0"}}, "Grassi monoinsaturi": {"Grassi Monoinsaturi 15:1": {"unit": "g", "amount": "0"}, "Grassi Monoinsaturi 16:1 indifferenziato": {"unit": "g", "amount": "0.004"}, "Grassi Monoinsaturi 17:1": {"unit": "g", "amount": "0"}, "Grassi Monoinsaturi 18:1 indifferenziato": {"unit": "g", "amount": "1.599"}, "Grassi Monoinsaturi 20:1": {"unit": "g", "amount": "0.001"}, "Grassi Monoinsaturi 22:1 indifferenziato": {"unit": "g", "amount": "0"}, "Grassi Monoinsaturi 24:1 c": {"unit": "g", "amount": "0"}}, "Grassi polinsaturi": {"Grassi Polinsaturi 18:2 indifferenziato": {"unit": "g", "amount": "0.234"}, "Grassi Polinsaturi 18:3 indifferenziato": {"unit": "g", "amount": "0.007"}, "Grassi Polinsaturi 18:4": {"unit": "g", "amount": "0"}, "Grassi Polinsaturi 20:2 n-6 c,c": {"unit": "g", "amount": "0"}, "Grassi Polinsaturi 20:3 indifferenziato": {"unit": "g", "amount": "0"}, "Grassi Polinsaturi 20:4 indifferenziato": {"unit": "g", "amount": "0"}, "20:5 n-3": {"unit": "g", "amount": "0"}, "22:5 n-3": {"unit": "g", "amount": "0"}, "22:6 n-3": {"unit": "g", "amount": "0"}}, "meta-data": ["bevande"]}