{"name": "crema_di_verdure", "Principali": {"Calorie": {"unit": "kj", "amount": "1866"}, "Grassi": {"unit": "g", "amount": "24.1"}, "Carboidrati": {"unit": "g", "amount": "52.1"}, "Proteine": {"unit": "g", "amount": "8"}, "Fibre": {"unit": "g", "amount": "3"}, "Zuccheri": {"unit": "g", "amount": "17.51"}, "Acqua": {"unit": "g", "amount": "2.9"}, "Ceneri": {"unit": "g", "amount": "12.9"}}, "Minerali": {"Calcio": {"unit": "mg", "amount": "134"}, "Sodio": {"unit": "mg", "amount": "4957"}, "Fosforo": {"unit": "mg", "amount": "228"}, "Potassio": {"unit": "mg", "amount": "408"}, "Ferro": {"unit": "mg", "amount": "2.6"}, "Magnesio": {"unit": "mg", "amount": "48"}, "Zinco": {"unit": "mg", "amount": "1.6"}, "Rame": {"unit": "mg", "amount": "0.4"}, "Manganese": {"unit": "mg", "amount": "0.8"}, "Selenio": {"unit": "mcg", "amount": "20.7"}}, "Vitamine": {"Retinolo (Vit. A)": {"unit": "mcg", "amount": "0"}, "Vitamina A, IU": {"unit": "IU", "amount": "11996"}, "Vitamina A, RAE": {"unit": "mcg_RAE", "amount": "600"}, "Tiamina (Vit. B1)": {"unit": "mg", "amount": "5.18"}, "Riboflavina (Vit. B2)": {"unit": "mg", "amount": "0.45"}, "Niacina (Vit. B3)": {"unit": "mg", "amount": "2.2"}, "Acido Pantotenico (Vit. B5)": {"unit": "mg", "amount": "0.7"}, "Piridossina (Vit. B6)": {"unit": "mg", "amount": "0.1"}, "Acido folico (Vit. B9 o M o Folacina)": {"unit": "mcg", "amount": "0"}, "Folato alimentare": {"unit": "mcg", "amount": "30"}, "Folato, DFE": {"unit": "mcg_DFE", "amount": "30"}, "Folati, totali": {"unit": "mcg", "amount": "30"}, "Cobalamina (Vit. B12)": {"unit": "mcg", "amount": "0.5"}, "Vitamina B-12, aggiunta": {"unit": "mcg", "amount": "0"}, "Acido ascorbico (Vit. C)": {"unit": "mg", "amount": "16.6"}, "Vitamina D (D2+D3)": {"unit": "mcg", "amount": "0"}, "Colecalcifenolo (Vit. D)": {"unit": "IU", "amount": "0"}, "Alpha-tocoferolo (Vit. E)": {"unit": "mg", "amount": "2.41"}, "Vitamina E, aggiunta": {"unit": "mg", "amount": "0"}, "Fillochinone (Vit. K)": {"unit": "mcg", "amount": "32.9"}, "Colina totale (Vit. J)": {"unit": "mg", "amount": "58"}, "Carotene, beta": {"unit": "mcg", "amount": "5620"}, "Carotene, alfa": {"unit": "mcg", "amount": "2820"}, "Criptoxantina, beta": {"unit": "mcg", "amount": "334"}, "Licopene": {"unit": "mcg", "amount": "2"}, "Luteina + zeaxantina": {"unit": "mcg", "amount": "920"}}, "Lipidi": {"Acidi grassi, monoinsaturi": {"unit": "g", "amount": "10.73"}, "Acidi grassi, polinsaturi": {"unit": "g", "amount": "6.29"}, "Acidi grassi, saturi": {"unit": "g", "amount": "6.03"}, "Colesterolo": {"unit": "mg", "amount": "2"}}, "Grassi saturi": {"4:0": {"unit": "g", "amount": "0"}, "6:0": {"unit": "g", "amount": "0"}, "8:0": {"unit": "g", "amount": "0"}, "Grassi Saturi 10:0": {"unit": "g", "amount": "0"}, "Grassi Saturi 12:0": {"unit": "g", "amount": "0"}, "Grassi Saturi 14:0": {"unit": "g", "amount": "0.1"}, "Grassi Saturi 16:0": {"unit": "g", "amount": "3.4"}, "Grassi Saturi 18:0": {"unit": "g", "amount": "2.56"}}, "Grassi monoinsaturi": {"Grassi Monoinsaturi 16:1 indifferenziato": {"unit": "g", "amount": "0"}, "Grassi Monoinsaturi 18:1 indifferenziato": {"unit": "g", "amount": "10.73"}, "Grassi Monoinsaturi 20:1": {"unit": "g", "amount": "0"}, "Grassi Monoinsaturi 22:1 indifferenziato": {"unit": "g", "amount": "0"}}, "Grassi polinsaturi": {"Grassi Polinsaturi 18:2 indifferenziato": {"unit": "g", "amount": "5.91"}, "Grassi Polinsaturi 18:3 indifferenziato": {"unit": "g", "amount": "0.39"}, "Grassi Polinsaturi 18:4": {"unit": "g", "amount": "0"}, "Grassi Polinsaturi 20:4 indifferenziato": {"unit": "g", "amount": "0"}, "20:5 n-3": {"unit": "g", "amount": "0"}, "22:5 n-3": {"unit": "g", "amount": "0"}, "22:6 n-3": {"unit": "g", "amount": "0"}}, "meta-data": ["zuppe", "salse e sughi"]}