{"name": "fagioli_giapponesi_azuki,_bolliti", "Principali": {"Calorie": {"unit": "kj", "amount": "536"}, "Grassi": {"unit": "g", "amount": "0.1"}, "Carboidrati": {"unit": "g", "amount": "24.77"}, "Proteine": {"unit": "g", "amount": "7.52"}, "Fibre": {"unit": "g", "amount": "7.3"}, "Acqua": {"unit": "g", "amount": "66.29"}, "Ceneri": {"unit": "g", "amount": "1.33"}}, "Minerali": {"Calcio": {"unit": "mg", "amount": "28"}, "Sodio": {"unit": "mg", "amount": "244"}, "Fosforo": {"unit": "mg", "amount": "168"}, "Potassio": {"unit": "mg", "amount": "532"}, "Ferro": {"unit": "mg", "amount": "2"}, "Magnesio": {"unit": "mg", "amount": "52"}, "Zinco": {"unit": "mg", "amount": "1.77"}, "Rame": {"unit": "mg", "amount": "0.298"}, "Manganese": {"unit": "mg", "amount": "0.573"}, "Selenio": {"unit": "mcg", "amount": "1.2"}}, "Vitamine": {"Retinolo (Vit. A)": {"unit": "mcg", "amount": "0"}, "Vitamina A, IU": {"unit": "IU", "amount": "6"}, "Vitamina A, RAE": {"unit": "mcg_RAE", "amount": "0"}, "Tiamina (Vit. B1)": {"unit": "mg", "amount": "0.115"}, "Riboflavina (Vit. B2)": {"unit": "mg", "amount": "0.064"}, "Niacina (Vit. B3)": {"unit": "mg", "amount": "0.717"}, "Acido Pantotenico (Vit. B5)": {"unit": "mg", "amount": "0.43"}, "Piridossina (Vit. B6)": {"unit": "mg", "amount": "0.096"}, "Acido folico (Vit. B9 o M o Folacina)": {"unit": "mcg", "amount": "0"}, "Folato alimentare": {"unit": "mcg", "amount": "121"}, "Folato, DFE": {"unit": "mcg_DFE", "amount": "121"}, "Folati, totali": {"unit": "mcg", "amount": "121"}, "Cobalamina (Vit. B12)": {"unit": "mcg", "amount": "0"}, "Acido ascorbico (Vit. C)": {"unit": "mg", "amount": "0"}, "Vitamina D (D2+D3)": {"unit": "mcg", "amount": "0"}, "Colecalcifenolo (Vit. D)": {"unit": "IU", "amount": "0"}}, "Lipidi": {"Acidi grassi, saturi": {"unit": "g", "amount": "0.036"}, "Colesterolo": {"unit": "mg", "amount": "0"}}, "Grassi monoinsaturi": {"Grassi Monoinsaturi 18:1 indifferenziato": {"unit": "g", "amount": "0.009"}}, "Grassi polinsaturi": {"Grassi Polinsaturi 18:2 indifferenziato": {"unit": "g", "amount": "0.021"}}, "Aminoacidi": {"Acido aspartico": {"unit": "g", "amount": "0.891"}, "Acido glutammico": {"unit": "g", "amount": "1.173"}, "Alanina": {"unit": "g", "amount": "0.439"}, "Arginina": {"unit": "g", "amount": "0.486"}, "Cistina": {"unit": "g", "amount": "0.07"}, "Fenilalanina": {"unit": "g", "amount": "0.398"}, "Glicina": {"unit": "g", "amount": "0.286"}, "Isoleucina": {"unit": "g", "amount": "0.3"}, "Istidina": {"unit": "g", "amount": "0.198"}, "Leucina": {"unit": "g", "amount": "0.632"}, "Lisina": {"unit": "g", "amount": "0.567"}, "Metionina": {"unit": "g", "amount": "0.079"}, "Prolina": {"unit": "g", "amount": "0.331"}, "Serina": {"unit": "g", "amount": "0.369"}, "Tirosina": {"unit": "g", "amount": "0.224"}, "Treonina": {"unit": "g", "amount": "0.255"}, "Triptofano": {"unit": "g", "amount": "0.072"}, "Valina": {"unit": "g", "amount": "0.387"}}, "meta-data": ["legumi e derivati"]}