{"name": "formaggio_svizzero,_basso_contenuto_di_grassi", "Principali": {"Calorie": {"unit": "kj", "amount": "724"}, "Grassi": {"unit": "g", "amount": "5.1"}, "Carboidrati": {"unit": "g", "amount": "3.4"}, "Proteine": {"unit": "g", "amount": "28.4"}, "Fibre": {"unit": "g", "amount": "0"}, "Zuccheri": {"unit": "g", "amount": "1.33"}, "Acqua": {"unit": "g", "amount": "59.6"}, "Ceneri": {"unit": "g", "amount": "3.5"}}, "Minerali": {"Calcio": {"unit": "mg", "amount": "961"}, "Sodio": {"unit": "mg", "amount": "260"}, "Fosforo": {"unit": "mg", "amount": "605"}, "Potassio": {"unit": "mg", "amount": "111"}, "Ferro": {"unit": "mg", "amount": "0.17"}, "Magnesio": {"unit": "mg", "amount": "36"}, "Zinco": {"unit": "mg", "amount": "3.9"}, "Rame": {"unit": "mg", "amount": "0.027"}, "Selenio": {"unit": "mcg", "amount": "12.7"}}, "Vitamine": {"Retinolo (Vit. A)": {"unit": "mcg", "amount": "39"}, "Vitamina A, IU": {"unit": "IU", "amount": "152"}, "Vitamina A, RAE": {"unit": "mcg_RAE", "amount": "40"}, "Tiamina (Vit. B1)": {"unit": "mg", "amount": "0.02"}, "Riboflavina (Vit. B2)": {"unit": "mg", "amount": "0.36"}, "Niacina (Vit. B3)": {"unit": "mg", "amount": "0.09"}, "Piridossina (Vit. B6)": {"unit": "mg", "amount": "0.08"}, "Acido folico (Vit. B9 o M o Folacina)": {"unit": "mcg", "amount": "0"}, "Folato alimentare": {"unit": "mcg", "amount": "6"}, "Folato, DFE": {"unit": "mcg_DFE", "amount": "6"}, "Folati, totali": {"unit": "mcg", "amount": "6"}, "Cobalamina (Vit. B12)": {"unit": "mcg", "amount": "1.68"}, "Vitamina B-12, aggiunta": {"unit": "mcg", "amount": "0"}, "Acido ascorbico (Vit. C)": {"unit": "mg", "amount": "0"}, "Vitamina D (D2+D3)": {"unit": "mcg", "amount": "0.1"}, "Vitamina D3": {"unit": "mcg", "amount": "0.1"}, "Colecalcifenolo (Vit. D)": {"unit": "IU", "amount": "4"}, "Alpha-tocoferolo (Vit. E)": {"unit": "mg", "amount": "0.07"}, "Vitamina E, aggiunta": {"unit": "mg", "amount": "0"}, "Fillochinone (Vit. K)": {"unit": "mcg", "amount": "0.5"}, "Colina totale (Vit. J)": {"unit": "mg", "amount": "15.4"}, "Carotene, beta": {"unit": "mcg", "amount": "13"}, "Carotene, alfa": {"unit": "mcg", "amount": "0"}, "Criptoxantina, beta": {"unit": "mcg", "amount": "0"}, "Licopene": {"unit": "mcg", "amount": "0"}, "Luteina + zeaxantina": {"unit": "mcg", "amount": "0"}}, "Lipidi": {"Acidi grassi, monoinsaturi": {"unit": "g", "amount": "1.351"}, "Acidi grassi, polinsaturi": {"unit": "g", "amount": "0.18"}, "Acidi grassi, saturi": {"unit": "g", "amount": "3.304"}, "Colesterolo": {"unit": "mg", "amount": "35"}}, "Grassi saturi": {"4:0": {"unit": "g", "amount": "0.204"}, "6:0": {"unit": "g", "amount": "0.091"}, "8:0": {"unit": "g", "amount": "0.054"}, "Grassi Saturi 10:0": {"unit": "g", "amount": "0.115"}, "Grassi Saturi 12:0": {"unit": "g", "amount": "0.097"}, "Grassi Saturi 14:0": {"unit": "g", "amount": "0.569"}, "Grassi Saturi 16:0": {"unit": "g", "amount": "1.447"}, "Grassi Saturi 18:0": {"unit": "g", "amount": "0.604"}}, "Grassi monoinsaturi": {"Grassi Monoinsaturi 16:1 indifferenziato": {"unit": "g", "amount": "0.164"}, "Grassi Monoinsaturi 18:1 indifferenziato": {"unit": "g", "amount": "1.119"}, "Grassi Monoinsaturi 20:1": {"unit": "g", "amount": "0"}, "Grassi Monoinsaturi 22:1 indifferenziato": {"unit": "g", "amount": "0"}}, "Grassi polinsaturi": {"Grassi Polinsaturi 18:2 indifferenziato": {"unit": "g", "amount": "0.115"}, "Grassi Polinsaturi 18:3 indifferenziato": {"unit": "g", "amount": "0.065"}, "Grassi Polinsaturi 18:4": {"unit": "g", "amount": "0"}, "Grassi Polinsaturi 20:4 indifferenziato": {"unit": "g", "amount": "0"}, "20:5 n-3": {"unit": "g", "amount": "0"}, "22:5 n-3": {"unit": "g", "amount": "0"}, "22:6 n-3": {"unit": "g", "amount": "0"}}, "meta-data": ["latticini e uova"]}