{"name": "hamburger,_fast_food", "Principali": {"Calorie": {"unit": "kj", "amount": "1234"}, "Grassi": {"unit": "g", "amount": "11.24"}, "Carboidrati": {"unit": "g", "amount": "33.71"}, "Proteine": {"unit": "g", "amount": "14.74"}, "Fibre": {"unit": "g", "amount": "1.2"}, "Zuccheri": {"unit": "g", "amount": "5.79"}, "Acqua": {"unit": "g", "amount": "38.49"}, "Ceneri": {"unit": "g", "amount": "1.86"}}, "Minerali": {"Calcio": {"unit": "mg", "amount": "138"}, "Sodio": {"unit": "mg", "amount": "440"}, "Fosforo": {"unit": "mg", "amount": "122"}, "Potassio": {"unit": "mg", "amount": "193"}, "Ferro": {"unit": "mg", "amount": "3.05"}, "Magnesio": {"unit": "mg", "amount": "21"}, "Zinco": {"unit": "mg", "amount": "2.2"}, "Rame": {"unit": "mg", "amount": "0.095"}, "Manganese": {"unit": "mg", "amount": "0.288"}}, "Vitamine": {"Retinolo (Vit. A)": {"unit": "mcg", "amount": "0"}, "Vitamina A, IU": {"unit": "IU", "amount": "0"}, "Betaina": {"unit": "mg", "amount": "41.3"}, "Vitamina A, RAE": {"unit": "mcg_RAE", "amount": "0"}, "Tiamina (Vit. B1)": {"unit": "mg", "amount": "0.293"}, "Riboflavina (Vit. B2)": {"unit": "mg", "amount": "0.28"}, "Niacina (Vit. B3)": {"unit": "mg", "amount": "5.342"}, "Acido Pantotenico (Vit. B5)": {"unit": "mg", "amount": "0.217"}, "Piridossina (Vit. B6)": {"unit": "mg", "amount": "0.142"}, "Folati, totali": {"unit": "mcg", "amount": "74"}, "Cobalamina (Vit. B12)": {"unit": "mcg", "amount": "1"}, "Acido ascorbico (Vit. C)": {"unit": "mg", "amount": "0"}, "Colina totale (Vit. J)": {"unit": "mg", "amount": "34.4"}}, "Zuccheri": {"Destrosio": {"unit": "g", "amount": "1.63"}, "Fruttosio": {"unit": "g", "amount": "2.83"}, "Galattosio": {"unit": "g", "amount": "0"}, "Lattosio": {"unit": "g", "amount": "0.18"}, "Maltosio": {"unit": "g", "amount": "0.84"}, "Saccarosio": {"unit": "g", "amount": "0.31"}}, "Lipidi": {"Acidi grassi, monoinsaturi": {"unit": "g", "amount": "3.839"}, "Acidi grassi, polinsaturi": {"unit": "g", "amount": "0.265"}, "Acidi grassi, saturi": {"unit": "g", "amount": "3.561"}, "Acidi grassi, trans": {"unit": "g", "amount": "0.569"}, "Colesterolo": {"unit": "mg", "amount": "33"}}, "Aminoacidi": {"Acido aspartico": {"unit": "g", "amount": "1.056"}, "Acido glutammico": {"unit": "g", "amount": "2.976"}, "Alanina": {"unit": "g", "amount": "0.745"}, "Arginina": {"unit": "g", "amount": "0.79"}, "Cistina": {"unit": "g", "amount": "0.173"}, "Fenilalanina": {"unit": "g", "amount": "0.583"}, "Glicina": {"unit": "g", "amount": "0.84"}, "Isoleucina": {"unit": "g", "amount": "0.579"}, "Istidina": {"unit": "g", "amount": "0.384"}, "Leucina": {"unit": "g", "amount": "1.049"}, "Lisina": {"unit": "g", "amount": "0.854"}, "Metionina": {"unit": "g", "amount": "0.282"}, "Prolina": {"unit": "g", "amount": "0.997"}, "Serina": {"unit": "g", "amount": "0.54"}, "Tirosina": {"unit": "g", "amount": "0.391"}, "Treonina": {"unit": "g", "amount": "0.513"}, "Triptofano": {"unit": "g", "amount": "0.168"}, "Valina": {"unit": "g", "amount": "0.674"}}, "meta-data": ["fast food"]}