{"name": "lepre,_carne_cruda", "Principali": {"Calorie": {"unit": "kj", "amount": "477"}, "Grassi": {"unit": "g", "amount": "2.32"}, "Carboidrati": {"unit": "g", "amount": "0"}, "Proteine": {"unit": "g", "amount": "21.79"}, "Fibre": {"unit": "g", "amount": "0"}, "Acqua": {"unit": "g", "amount": "74.51"}, "Ceneri": {"unit": "g", "amount": "1.12"}}, "Minerali": {"Calcio": {"unit": "mg", "amount": "12"}, "Sodio": {"unit": "mg", "amount": "50"}, "Fosforo": {"unit": "mg", "amount": "226"}, "Potassio": {"unit": "mg", "amount": "378"}, "Ferro": {"unit": "mg", "amount": "3.2"}, "Magnesio": {"unit": "mg", "amount": "29"}, "Selenio": {"unit": "mcg", "amount": "9.4"}}, "Vitamine": {"Retinolo (Vit. A)": {"unit": "mcg", "amount": "0"}, "Vitamina A, IU": {"unit": "IU", "amount": "0"}, "Vitamina A, RAE": {"unit": "mcg_RAE", "amount": "0"}, "Tiamina (Vit. B1)": {"unit": "mg", "amount": "0.03"}, "Riboflavina (Vit. B2)": {"unit": "mg", "amount": "0.06"}, "Niacina (Vit. B3)": {"unit": "mg", "amount": "6.5"}, "Acido ascorbico (Vit. C)": {"unit": "mg", "amount": "0"}}, "Lipidi": {"Acidi grassi, monoinsaturi": {"unit": "g", "amount": "0.63"}, "Acidi grassi, polinsaturi": {"unit": "g", "amount": "0.45"}, "Acidi grassi, saturi": {"unit": "g", "amount": "0.69"}, "Colesterolo": {"unit": "mg", "amount": "81"}}, "Grassi saturi": {"Grassi Saturi 14:0": {"unit": "g", "amount": "0.06"}, "Grassi Saturi 16:0": {"unit": "g", "amount": "0.52"}, "Grassi Saturi 18:0": {"unit": "g", "amount": "0.11"}}, "Grassi monoinsaturi": {"Grassi Monoinsaturi 16:1 indifferenziato": {"unit": "g", "amount": "0.08"}, "Grassi Monoinsaturi 18:1 indifferenziato": {"unit": "g", "amount": "0.54"}}, "Grassi polinsaturi": {"Grassi Polinsaturi 18:2 indifferenziato": {"unit": "g", "amount": "0.36"}, "Grassi Polinsaturi 18:3 indifferenziato": {"unit": "g", "amount": "0.09"}}, "Aminoacidi": {"Acido aspartico": {"unit": "g", "amount": "2.129"}, "Acido glutammico": {"unit": "g", "amount": "3.496"}, "Alanina": {"unit": "g", "amount": "1.315"}, "Arginina": {"unit": "g", "amount": "1.346"}, "Cistina": {"unit": "g", "amount": "0.274"}, "Fenilalanina": {"unit": "g", "amount": "0.895"}, "Glicina": {"unit": "g", "amount": "1.183"}, "Isoleucina": {"unit": "g", "amount": "1.034"}, "Istidina": {"unit": "g", "amount": "0.611"}, "Leucina": {"unit": "g", "amount": "1.698"}, "Lisina": {"unit": "g", "amount": "1.908"}, "Metionina": {"unit": "g", "amount": "0.545"}, "Prolina": {"unit": "g", "amount": "1.065"}, "Serina": {"unit": "g", "amount": "0.966"}, "Tirosina": {"unit": "g", "amount": "0.776"}, "Treonina": {"unit": "g", "amount": "0.975"}, "Triptofano": {"unit": "g", "amount": "0.288"}, "Valina": {"unit": "g", "amount": "1.108"}}, "meta-data": ["agnello", "vitello", "cacciagione"]}