{"name": "pancetta_di_maiale,_grassa", "Principali": {"Calorie": {"unit": "kj", "amount": "3756"}, "Grassi": {"unit": "g", "amount": "99.5"}, "Carboidrati": {"unit": "g", "amount": "0"}, "Proteine": {"unit": "g", "amount": "0.07"}, "Fibre": {"unit": "g", "amount": "0"}, "Zuccheri": {"unit": "g", "amount": "0"}, "Acqua": {"unit": "g", "amount": "0.25"}, "Ceneri": {"unit": "g", "amount": "0.16"}}, "Minerali": {"Calcio": {"unit": "mg", "amount": "1"}, "Sodio": {"unit": "mg", "amount": "27"}, "Fosforo": {"unit": "mg", "amount": "9"}, "Potassio": {"unit": "mg", "amount": "15"}, "Ferro": {"unit": "mg", "amount": "0.13"}, "Magnesio": {"unit": "mg", "amount": "0"}, "Zinco": {"unit": "mg", "amount": "0.06"}, "Rame": {"unit": "mg", "amount": "0.022"}, "Manganese": {"unit": "mg", "amount": "0.006"}, "Selenio": {"unit": "mcg", "amount": "5.7"}}, "Vitamine": {"Retinolo (Vit. A)": {"unit": "mcg", "amount": "11"}, "Betaina": {"unit": "mg", "amount": "0.2"}, "Vitamina A, IU": {"unit": "IU", "amount": "37"}, "Vitamina A, RAE": {"unit": "mcg_RAE", "amount": "11"}, "Tiamina (Vit. B1)": {"unit": "mg", "amount": "0.004"}, "Riboflavina (Vit. B2)": {"unit": "mg", "amount": "0.015"}, "Niacina (Vit. B3)": {"unit": "mg", "amount": "0.725"}, "Acido Pantotenico (Vit. B5)": {"unit": "mg", "amount": "0.007"}, "Piridossina (Vit. B6)": {"unit": "mg", "amount": "0.005"}, "Acido folico (Vit. B9 o M o Folacina)": {"unit": "mcg", "amount": "0"}, "Folato alimentare": {"unit": "mcg", "amount": "0"}, "Folato, DFE": {"unit": "mcg_DFE", "amount": "0"}, "Folati, totali": {"unit": "mcg", "amount": "0"}, "Cobalamina (Vit. B12)": {"unit": "mcg", "amount": "0.09"}, "Vitamina B-12, aggiunta": {"unit": "mcg", "amount": "0"}, "Acido ascorbico (Vit. C)": {"unit": "mg", "amount": "0"}, "Alpha-tocoferolo (Vit. E)": {"unit": "mg", "amount": "0"}, "Vitamina E, aggiunta": {"unit": "mg", "amount": "0"}, "Fillochinone (Vit. K)": {"unit": "mcg", "amount": "0"}, "Colina totale (Vit. J)": {"unit": "mg", "amount": "6.5"}, "Carotene, beta": {"unit": "mcg", "amount": "0"}, "Carotene, alfa": {"unit": "mcg", "amount": "0"}, "Criptoxantina, beta": {"unit": "mcg", "amount": "0"}, "Licopene": {"unit": "mcg", "amount": "0"}, "Luteina + zeaxantina": {"unit": "mcg", "amount": "0"}}, "Lipidi": {"Acidi grassi, monoinsaturi": {"unit": "g", "amount": "41.435"}, "Acidi grassi, polinsaturi": {"unit": "g", "amount": "10.535"}, "Acidi grassi, saturi": {"unit": "g", "amount": "31.991"}, "Acidi grassi, trans": {"unit": "g", "amount": "0"}, "Colesterolo": {"unit": "mg", "amount": "97"}}, "Grassi saturi": {"4:0": {"unit": "g", "amount": "0"}, "6:0": {"unit": "g", "amount": "0"}, "8:0": {"unit": "g", "amount": "0"}, "Grassi Saturi 10:0": {"unit": "g", "amount": "0"}, "Grassi Saturi 12:0": {"unit": "g", "amount": "0"}, "Grassi Saturi 14:0": {"unit": "g", "amount": "1.32"}, "Grassi Saturi 15:0": {"unit": "g", "amount": "0"}, "Grassi Saturi 16:0": {"unit": "g", "amount": "19.762"}, "Grassi Saturi 17:0": {"unit": "g", "amount": "0.274"}, "Grassi Saturi 18:0": {"unit": "g", "amount": "10.443"}, "Grassi Saturi 20:0": {"unit": "g", "amount": "0.192"}, "Grassi Saturi 22:0": {"unit": "g", "amount": "0"}}, "Grassi monoinsaturi": {"Grassi Monoinsaturi 14:1": {"unit": "g", "amount": "0"}, "Grassi Monoinsaturi 15:1": {"unit": "g", "amount": "0"}, "Grassi Monoinsaturi 16:1 indifferenziato": {"unit": "g", "amount": "2.86"}, "Grassi Monoinsaturi 17:1": {"unit": "g", "amount": "0"}, "Grassi Monoinsaturi 18:1 indifferenziato": {"unit": "g", "amount": "37.818"}, "Grassi Monoinsaturi 20:1": {"unit": "g", "amount": "0.757"}, "Grassi Monoinsaturi 22:1 indifferenziato": {"unit": "g", "amount": "0"}}, "Grassi polinsaturi": {"Grassi Polinsaturi 18:2 indifferenziato": {"unit": "g", "amount": "9.426"}, "Grassi Polinsaturi 18:2 n-6 c,c": {"unit": "g", "amount": "9.426"}, "Grassi Polinsaturi 18:3 indifferenziato": {"unit": "g", "amount": "0.476"}, "Grassi Polinsaturi 18:3 n-3 c,c,c": {"unit": "g", "amount": "0.476"}, "Grassi Polinsaturi 18:3 n-6 c,c,c": {"unit": "g", "amount": "0"}, "Grassi Polinsaturi 18:4": {"unit": "g", "amount": "0"}, "Grassi Polinsaturi 20:2 n-6 c,c": {"unit": "g", "amount": "0.442"}, "Grassi Polinsaturi 20:3 indifferenziato": {"unit": "g", "amount": "0"}, "Grassi Polinsaturi 20:4 indifferenziato": {"unit": "g", "amount": "0.191"}, "20:5 n-3": {"unit": "g", "amount": "0"}, "22:5 n-3": {"unit": "g", "amount": "0"}, "22:6 n-3": {"unit": "g", "amount": "0"}}, "meta-data": ["maiale"]}