{"name": "succo_di_mirtilli_e_albicocca", "Principali": {"Calorie": {"unit": "kj", "amount": "268"}, "Grassi": {"unit": "g", "amount": "0"}, "Carboidrati": {"unit": "g", "amount": "16.2"}, "Proteine": {"unit": "g", "amount": "0.2"}, "Fibre": {"unit": "g", "amount": "0.1"}, "Acqua": {"unit": "g", "amount": "83.5"}, "Ceneri": {"unit": "g", "amount": "0.1"}}, "Minerali": {"Calcio": {"unit": "mg", "amount": "9"}, "Sodio": {"unit": "mg", "amount": "2"}, "Fosforo": {"unit": "mg", "amount": "5"}, "Potassio": {"unit": "mg", "amount": "61"}, "Ferro": {"unit": "mg", "amount": "0.15"}, "Magnesio": {"unit": "mg", "amount": "3"}, "Zinco": {"unit": "mg", "amount": "0.04"}, "Rame": {"unit": "mg", "amount": "0.015"}, "Manganese": {"unit": "mg", "amount": "0.125"}, "Selenio": {"unit": "mcg", "amount": "0"}}, "Vitamine": {"Retinolo (Vit. A)": {"unit": "mcg", "amount": "0"}, "Vitamina A, IU": {"unit": "IU", "amount": "463"}, "Vitamina A, RAE": {"unit": "mcg_RAE", "amount": "23"}, "Tiamina (Vit. B1)": {"unit": "mg", "amount": "0.005"}, "Riboflavina (Vit. B2)": {"unit": "mg", "amount": "0.01"}, "Niacina (Vit. B3)": {"unit": "mg", "amount": "0.12"}, "Acido Pantotenico (Vit. B5)": {"unit": "mg", "amount": "0.036"}, "Piridossina (Vit. B6)": {"unit": "mg", "amount": "0.02"}, "Acido folico (Vit. B9 o M o Folacina)": {"unit": "mcg", "amount": "0"}, "Folato alimentare": {"unit": "mcg", "amount": "1"}, "Folato, DFE": {"unit": "mcg_DFE", "amount": "1"}, "Folati, totali": {"unit": "mcg", "amount": "1"}, "Cobalamina (Vit. B12)": {"unit": "mcg", "amount": "0"}, "Acido ascorbico (Vit. C)": {"unit": "mg", "amount": "0"}}, "Lipidi": {"Acidi grassi, monoinsaturi": {"unit": "g", "amount": "0"}, "Acidi grassi, polinsaturi": {"unit": "g", "amount": "0"}, "Acidi grassi, saturi": {"unit": "g", "amount": "0"}, "Colesterolo": {"unit": "mg", "amount": "0"}}, "Grassi monoinsaturi": {"Grassi Monoinsaturi 18:1 indifferenziato": {"unit": "g", "amount": "0"}}, "Grassi polinsaturi": {"Grassi Polinsaturi 18:2 indifferenziato": {"unit": "g", "amount": "0"}}, "meta-data": ["bevande"]}