{"name": "yogurt_greco_da_latte_intero", "Principali": {"Calorie": {"unit": "kj", "amount": "481"}, "Grassi": {"unit": "g", "amount": "9.1"}, "Carboidrati": {"unit": "g", "amount": "2"}, "Proteine": {"unit": "g", "amount": "6.4"}, "Fibre": {"unit": "g", "amount": "0"}, "Acqua": {"unit": "g", "amount": "78.5"}, "Amido": {"unit": "g", "amount": "0"}}, "Minerali": {"Calcio": {"unit": "mg", "amount": "150"}, "Sodio": {"unit": "mg", "amount": "71"}, "Fosforo": {"unit": "mg", "amount": "130"}, "Potassio": {"unit": "mg", "amount": "150"}, "Ferro": {"unit": "mg", "amount": "0.3"}}, "Vitamine": {"Retinolo (Vit. A)": {"unit": "mcg", "amount": "121"}, "Tiamina (Vit. B1)": {"unit": "mg", "amount": "0.03"}, "Riboflavina (Vit. B2)": {"unit": "mg", "amount": "0.36"}, "Niacina (Vit. B3)": {"unit": "mg", "amount": "0.1"}}, "Zuccheri": {"Saccarosio": {"unit": "g", "amount": "2"}}, "meta-data": ["latticini e uova"]}