{"name": "zuppa_di_miso", "Principali": {"Calorie": {"unit": "kj", "amount": "831"}, "Grassi": {"unit": "g", "amount": "6.01"}, "Carboidrati": {"unit": "g", "amount": "26.47"}, "Proteine": {"unit": "g", "amount": "11.69"}, "Fibre": {"unit": "g", "amount": "5.4"}, "Zuccheri": {"unit": "g", "amount": "6.2"}, "Acqua": {"unit": "g", "amount": "43.02"}, "Ceneri": {"unit": "g", "amount": "12.81"}}, "Minerali": {"Calcio": {"unit": "mg", "amount": "57"}, "Sodio": {"unit": "mg", "amount": "3728"}, "Fosforo": {"unit": "mg", "amount": "159"}, "Potassio": {"unit": "mg", "amount": "210"}, "Ferro": {"unit": "mg", "amount": "2.49"}, "Magnesio": {"unit": "mg", "amount": "48"}, "Zinco": {"unit": "mg", "amount": "2.56"}, "Rame": {"unit": "mg", "amount": "0.42"}, "Manganese": {"unit": "mg", "amount": "0.859"}, "Selenio": {"unit": "mcg", "amount": "7"}}, "Vitamine": {"Retinolo (Vit. A)": {"unit": "mcg", "amount": "0"}, "Vitamina A, IU": {"unit": "IU", "amount": "87"}, "Vitamina A, RAE": {"unit": "mcg_RAE", "amount": "4"}, "Tiamina (Vit. B1)": {"unit": "mg", "amount": "0.098"}, "Riboflavina (Vit. B2)": {"unit": "mg", "amount": "0.233"}, "Niacina (Vit. B3)": {"unit": "mg", "amount": "0.906"}, "Acido Pantotenico (Vit. B5)": {"unit": "mg", "amount": "0.337"}, "Piridossina (Vit. B6)": {"unit": "mg", "amount": "0.199"}, "Acido folico (Vit. B9 o M o Folacina)": {"unit": "mcg", "amount": "0"}, "Folato alimentare": {"unit": "mcg", "amount": "19"}, "Folato, DFE": {"unit": "mcg_DFE", "amount": "19"}, "Folati, totali": {"unit": "mcg", "amount": "19"}, "Cobalamina (Vit. B12)": {"unit": "mcg", "amount": "0.08"}, "Vitamina B-12, aggiunta": {"unit": "mcg", "amount": "0"}, "Acido ascorbico (Vit. C)": {"unit": "mg", "amount": "0"}, "Vitamina D (D2+D3)": {"unit": "mcg", "amount": "0"}, "Colecalcifenolo (Vit. D)": {"unit": "IU", "amount": "0"}, "Alpha-tocoferolo (Vit. E)": {"unit": "mg", "amount": "0.01"}, "Vitamina E, aggiunta": {"unit": "mg", "amount": "0"}, "Fillochinone (Vit. K)": {"unit": "mcg", "amount": "29.3"}, "Colina totale (Vit. J)": {"unit": "mg", "amount": "72.2"}, "Carotene, beta": {"unit": "mcg", "amount": "52"}, "Carotene, alfa": {"unit": "mcg", "amount": "0"}, "Criptoxantina, beta": {"unit": "mcg", "amount": "0"}, "Licopene": {"unit": "mcg", "amount": "0"}, "Luteina + zeaxantina": {"unit": "mcg", "amount": "0"}}, "Zuccheri": {"Destrosio": {"unit": "g", "amount": "0"}, "Fruttosio": {"unit": "g", "amount": "6"}, "Galattosio": {"unit": "g", "amount": "0"}, "Lattosio": {"unit": "g", "amount": "0"}, "Maltosio": {"unit": "g", "amount": "0.2"}, "Saccarosio": {"unit": "g", "amount": "0"}}, "Lipidi": {"Acidi grassi, monoinsaturi": {"unit": "g", "amount": "1.242"}, "Acidi grassi, polinsaturi": {"unit": "g", "amount": "3.204"}, "Acidi grassi, saturi": {"unit": "g", "amount": "1.139"}, "Colesterolo": {"unit": "mg", "amount": "0"}}, "Grassi saturi": {"4:0": {"unit": "g", "amount": "0"}, "6:0": {"unit": "g", "amount": "0"}, "8:0": {"unit": "g", "amount": "0"}, "Grassi Saturi 10:0": {"unit": "g", "amount": "0"}, "Grassi Saturi 12:0": {"unit": "g", "amount": "0"}, "Grassi Saturi 13:0": {"unit": "g", "amount": "0"}, "Grassi Saturi 14:0": {"unit": "g", "amount": "0.017"}, "Grassi Saturi 15:0": {"unit": "g", "amount": "0"}, "Grassi Saturi 16:0": {"unit": "g", "amount": "0.833"}, "Grassi Saturi 17:0": {"unit": "g", "amount": "0.011"}, "Grassi Saturi 18:0": {"unit": "g", "amount": "0.222"}, "Grassi Saturi 20:0": {"unit": "g", "amount": "0"}, "Grassi Saturi 22:0": {"unit": "g", "amount": "0.056"}, "Grassi Saturi 24:0": {"unit": "g", "amount": "0"}}, "Grassi monoinsaturi": {"Grassi Monoinsaturi 14:1": {"unit": "g", "amount": "0"}, "Grassi Monoinsaturi 15:1": {"unit": "g", "amount": "0.022"}, "Grassi Monoinsaturi 16:1 indifferenziato": {"unit": "g", "amount": "0"}, "Grassi Monoinsaturi 17:1": {"unit": "g", "amount": "0.033"}, "Grassi Monoinsaturi 18:1 indifferenziato": {"unit": "g", "amount": "1.158"}, "Grassi Monoinsaturi 20:1": {"unit": "g", "amount": "0.028"}, "Grassi Monoinsaturi 22:1 indifferenziato": {"unit": "g", "amount": "0"}}, "Grassi polinsaturi": {"Grassi Polinsaturi 18:2 indifferenziato": {"unit": "g", "amount": "2.754"}, "Grassi Polinsaturi 18:3 indifferenziato": {"unit": "g", "amount": "0.45"}, "Grassi Polinsaturi 18:4": {"unit": "g", "amount": "0"}, "Grassi Polinsaturi 20:2 n-6 c,c": {"unit": "g", "amount": "0"}, "Grassi Polinsaturi 20:3 indifferenziato": {"unit": "g", "amount": "0"}, "Grassi Polinsaturi 20:4 indifferenziato": {"unit": "g", "amount": "0"}, "20:5 n-3": {"unit": "g", "amount": "0"}, "22:5 n-3": {"unit": "g", "amount": "0"}, "22:6 n-3": {"unit": "g", "amount": "0"}}, "Aminoacidi": {"Acido aspartico": {"unit": "g", "amount": "1.171"}, "Acido glutammico": {"unit": "g", "amount": "1.915"}, "Alanina": {"unit": "g", "amount": "0.5"}, "Arginina": {"unit": "g", "amount": "0.784"}, "Cistina": {"unit": "g", "amount": "0"}, "Fenilalanina": {"unit": "g", "amount": "0.486"}, "Glicina": {"unit": "g", "amount": "0.447"}, "Isoleucina": {"unit": "g", "amount": "0.508"}, "Istidina": {"unit": "g", "amount": "0.243"}, "Leucina": {"unit": "g", "amount": "0.82"}, "Lisina": {"unit": "g", "amount": "0.478"}, "Metionina": {"unit": "g", "amount": "0.129"}, "Prolina": {"unit": "g", "amount": "0.619"}, "Serina": {"unit": "g", "amount": "0.601"}, "Tirosina": {"unit": "g", "amount": "0.352"}, "Treonina": {"unit": "g", "amount": "0.479"}, "Triptofano": {"unit": "g", "amount": "0.155"}, "Valina": {"unit": "g", "amount": "0.547"}}, "meta-data": ["legumi e derivati"]}