{"name": "PIADINA \u2014 PICA \u2014 600 G", "barcode": "8058456620015", "ingredients": "Farina di _grano_tenero italiano,acqua, strutto di puro suino, sale, agente lievitante (difosfato disodico,carbonato di sodio, amido di _frumento).\r\nAllergeni(glutine)", "additives": "E450i - Difosfato disodico\nE500i - Carbonato di sodio", "nova": "", "Nome generico": " PIADINA", "Quantit\u00e0": " 600 G", "Confezionamento": " ATM", "Marche": " PICA", "Categorie": " PRODOTTO DA FORNO", "Origine degli ingredienti": " ITALIA, COMUNITARI", "Luoghi di produzione o lavorazione": " ITALIA", "Link alla pagina del prodotto sul sito ufficiale del produttore": " www.piadinaromagnolarimini.it", "Paesi di vendita": " Italia"}