{"name": "Balocco La colomba \u2014 750 g", "barcode": "8001100050829", "ingredients": "farina di FRUMENTO - scorze d'arancia candite 16,3% (scorze d'arancia - sciroppo di glucosio-fruttosio - zucchero - correttore di acidit\u00e0: acido citrico) - glassa alle NOCCIOLE 10,4% (zucchero - albume d'UOVO - NOCCIOLE 14,3% corrispondente al 1,5% del totale ingredienti - farina di FRUMENTO - olio d'ARACHIDE - mandorle d'albicocca - aromi) - BURRO - zucchero - tuorlo d'UOVA fresche - lievito naturale (FRUMENTO) - granella di zucchero - MANDORLE - emulsionanti: mono e digliceridi acidi grassi (di origine vegetale) - sciroppo di zucchero invertito - sale - LATTE scremato in polvere - aromi. Pu\u00f2 contenere tracce di altra frutta a guscio e soia.", "additives": "E330 - Acido citrico", "nova": "", "Nome generico": " Colomba - Prodotto da forno a lievitazione naturale", "Quantit\u00e0": " 750 g", "Confezionamento": " Astuccio, Cartone, Sacchetto, Plastica", "Marche": " Balocco, Balocco S.p.A. Via S. Lucia 51 12045 Fossano CN Italy", "Categorie": " Colomba, Dolce, Prodotto da forno", "Paesi di vendita": " Italia"}