{"name": "Colomba Dolci Frutti Coop \u2014 Coop - Fior fiore \u2014 1000 g", "barcode": "", "ingredients": "Farina di grano tenero tipo \"0\", Frutta disidratata e zuccherata 27,5% (in proporzione variabile: ananas 12,3%, papaya 9,7%, guava 3,5% e jack fruit (giaca) 2%, zucchero), Burro, Zucchero, Tuorlo d'uova fresche , Lievito madre naturale (farina di frumento, acqua) , Emulsionanti: mono e digliceridi degli acidi grassi , Latte intero fresco pastorizzato , Sciroppo di zucchero invertito , Sale, Aromi naturali , Ingredienti bustina di zucchero a velo: zucchero, amido di frumento, vanillina,", "additives": "E471 - Mono- e digliceridi degli acidi grassi", "nova": "", "Nome generico": " Colomba", "Quantit\u00e0": " 1000 g", "Confezionamento": " sacchetto plastica  + scatola cartone", "Marche": " Coop - Fior fiore", "Categorie": " Dolce da ricorrenza", "Paesi di vendita": " Italia"}