{"C4:1": ["acido crotonico"], "C4:2": ["acido aspartico"], "C5:2": ["acido glutammico"], "C9:1": ["acido pantotenico"], "C13:0": ["acido triglicerico"], "C18:2": ["acido oleico", "acido linoleico", "acido rumenico"], "C18:3": ["acido linoleico", "acido \u03b1-linolenico", "acido \u03b3-linolenico"], "C20:2": ["acido gadoleico"], "C20:5": ["acido eicosapentaenoico", "acido timnodonico, EPA"], "C22:1 undifferentiated": ["acido erucico"], "C22:6": ["acido docosaesaenoico", "acido cervonico, DHA"], "C24:1 c": ["acido nevronico"], "C4:0": ["acido butirrico"], "C5:0": ["acido valerico (valerianico)"], "C6:0": ["acido capronico"], "C7:0": ["acido enantico"], "C8:0": ["acido caprilico"], "C9:0": ["acido pelargonico"], "C10:0": ["acido caprico"], "C12:0": ["acido laurico"], "C14:0": ["acido miristico"], "C16:0": ["acido palmitico"], "C17:0": ["acido margarico"], "C18:0": ["acido stearico"], "C20:0": ["acido arachico"], "C22:0": ["acido beenico"], "C24:0": ["acido lignocerico"], "C26:0": ["acido cerotico"], "C28:0": ["acido montanico"], "C30:0": ["acido melissico"], "C32:0": ["acido laceroico"], "C14:1": ["acido miristoleico"], "C16:1": ["acido sapienico", "acido palmitoleico"], "C17:1": ["acido eptadecenoico"], "C18:1": ["acido oleico", "acido elaidinico", "acido vaccenicoacido trans-vaccenico", "acido asclepicoacido cis-vaccenico", "acido petroselinico", "acido petroselaidico"], "C20:1": ["acido gadoleico", "acido gondoico"], "C22:1": ["acido cetoleico", "acido erucico"], "C24:1": ["acido nervonico"], "C18:4": ["acido stearidonico"], "C20:4": ["acido arachidonico"], "C22:5": ["acido clupanodonico, DPA"]}